FTSAAppiumLibrary/__init__.py
FTSADatabaseLibrary/__init__.py
FTSARequestsLibrary/__init__.py
FTSASSHLibrary/__init__.py
FTSASeleniumLibrary/__init__.py
ftsa/__init__.py
ftsa/core/__init__.py
ftsa/core/properties.py
ftsa/core/utils/__init__.py
ftsa_tjpb_core-2.6.1.dist-info/LICENSE
ftsa_tjpb_core-2.6.1.dist-info/METADATA
ftsa_tjpb_core-2.6.1.dist-info/WHEEL
ftsa_tjpb_core-2.6.1.dist-info/top_level.txt
ftsa_tjpb_core-2.6.1.dist-info/RECORD
