Metadata-Version: 2.1
Name: ftsa-tjpb-core
Version: 2.6.1
Summary: Framework de Teste de Sistemas Automatizado - CORE
Home-page: http://gitlab-novo.tjpb.jus.br/testes/ftsa/core
Author: Carlos Diego Quirino Lima
Author-email: diegoquirino@gmail.com
License: UNKNOWN
Keywords: ftsa framework teste sistemas e2e automatizado tjpb core FTSADatabaseLibrary FTSASeleniumLibrary FTSASSHLibrary FTSAAppiumLibraryFTSARequestsLibrary
Platform: windows linux mac
Classifier: Programming Language :: Python :: 3
Classifier: License :: OSI Approved :: MIT License
Classifier: Operating System :: OS Independent
Requires-Python: >=3.6
License-File: LICENSE
Requires-Dist: robotframework
Requires-Dist: robotframework-seleniumlibrary
Requires-Dist: robotframework-sshlibrary
Requires-Dist: robotframework-databaselibrary
Requires-Dist: robotframework-appiumlibrary
Requires-Dist: robotframework-requests
Requires-Dist: robotframework-faker
Requires-Dist: selenium
Requires-Dist: webdrivermanager
Requires-Dist: docker
Requires-Dist: setuptools
Requires-Dist: wheel
Requires-Dist: twine
